XStatic_Spin-1.2.5.3-py3.6-nspkg.pth
xstatic/pkg/spin/__init__.py
xstatic/pkg/spin/data/spin.jquery.js
xstatic/pkg/spin/data/spin.js
XStatic_Spin-1.2.5.3.dist-info/METADATA
XStatic_Spin-1.2.5.3.dist-info/WHEEL
XStatic_Spin-1.2.5.3.dist-info/namespace_packages.txt
XStatic_Spin-1.2.5.3.dist-info/top_level.txt
XStatic_Spin-1.2.5.3.dist-info/RECORD
