Metadata-Version: 2.1
Name: XStatic-Spin
Version: 1.2.5.3
Summary: Spin 1.2.5 (XStatic packaging standard)
Home-page: http://fgnass.github.io/spin.js/
Maintainer: Radomir Dopieralski
Maintainer-email: openstack@sheep.art.pl
License: (same as Spin)
Keywords: spin xstatic
Platform: any
